README
casconfig.py
setup.py
casconfig.egg-info/PKG-INFO
casconfig.egg-info/SOURCES.txt
casconfig.egg-info/dependency_links.txt
casconfig.egg-info/requires.txt
casconfig.egg-info/top_level.txt