Metadata-Version: 1.0
Name: casconfig
Version: 0.0.1
Summary: Tiered cascading simple configs
Home-page: https://github.com/rranshous/casconfig
Author: Robby Ranshous
Author-email: rranshous@gmail.com
License: UNKNOWN
Keywords: configuration
Platform: UNKNOWN
Classifier: Development Status :: 3 - Alpha
Classifier: Topic :: Utilities
Classifier: Programming Language :: Python :: 2.6
Classifier: Programming Language :: Python :: 2.7
